kaiju_model/__init__.py
kaiju_model/fields.py
kaiju_model/model.py
kaiju_model/grid/__init__.py
kaiju_model/grid/base.py
kaiju_model/grid/constructor.py
kaiju_model/tests/__init__.py
kaiju_model-2.2.3.dist-info/LICENSE
kaiju_model-2.2.3.dist-info/METADATA
kaiju_model-2.2.3.dist-info/WHEEL
kaiju_model-2.2.3.dist-info/top_level.txt
kaiju_model-2.2.3.dist-info/RECORD
